humem/__init__.py
humem/core.py
humem/exceptions.py
humem/models.py
humem/storage.py
humem-0.1.0.dist-info/licenses/LICENSE
humem-0.1.0.dist-info/METADATA
humem-0.1.0.dist-info/WHEEL
humem-0.1.0.dist-info/top_level.txt
humem-0.1.0.dist-info/RECORD
