Metadata-Version: 2.4
Name: humem
Version: 0.1.0
Summary: A memory management system for AI agents to store and retrieve user interactions
Home-page: https://github.com/yourusername/humem
Author: Your Name
Author-email: Your Name <your.email@example.com>
License: MIT
Project-URL: Homepage, https://github.com/yourusername/humem
Project-URL: Bug Reports, https://github.com/yourusername/humem/issues
Project-URL: Source, https://github.com/yourusername/humem
Project-URL: Documentation, https://github.com/yourusername/humem#readme
Keywords: ai,memory,agent,llm,chatbot,conversation
Classifier: Development Status :: 3 - Alpha
Classifier: Intended Audience :: Developers
Classifier: License :: OSI Approved :: MIT License
Classifier: Operating System :: OS Independent
Classifier: Programming Language :: Python :: 3
Classifier: Programming Language :: Python :: 3.8
Classifier: Programming Language :: Python :: 3.9
Classifier: Programming Language :: Python :: 3.10
Classifier: Programming Language :: Python :: 3.11
Classifier: Programming Language :: Python :: 3.12
Classifier: Topic :: Software Development :: Libraries :: Python Modules
Classifier: Topic :: Scientific/Engineering :: Artificial Intelligence
Requires-Python: >=3.8
License-File: LICENSE
Requires-Dist: sqlalchemy>=2.0.0
Requires-Dist: typing-extensions>=4.0.0
Requires-Dist: pydantic>=2.0.0
Requires-Dist: python-dateutil>=2.8.0
Provides-Extra: dev
Requires-Dist: pytest>=7.0.0; extra == "dev"
Requires-Dist: pytest-cov>=4.0.0; extra == "dev"
Requires-Dist: black>=23.0.0; extra == "dev"
Requires-Dist: isort>=5.12.0; extra == "dev"
Requires-Dist: flake8>=6.0.0; extra == "dev"
Requires-Dist: mypy>=1.0.0; extra == "dev"
Dynamic: author
Dynamic: home-page
Dynamic: license-file
Dynamic: requires-python
